mnltools/__init__.py
mnltools/dt/__init__.py
mnltools/dt/dsp2rsd.py
mnltools/dt/sound/__init__.py
mnltools/dt/sound/repacker.py
mnltools/nds/__init__.py
mnltools/nds/packer.py
mnltools/nds/unpacker.py
mnltools/py.typed
mnltools-1.0.1.dist-info/LICENSE
mnltools-1.0.1.dist-info/METADATA
mnltools-1.0.1.dist-info/WHEEL
mnltools-1.0.1.dist-info/entry_points.txt
mnltools-1.0.1.dist-info/RECORD
