Metadata-Version: 2.3
Name: mnltools
Version: 1.0.1
Summary: Python tools for the Mario & Luigi games.
License: GPL-3.0-or-later
Author: Dimitar Dimitrov
Author-email: dmtrdmtrov@gmail.com
Requires-Python: >=3.12,<4.0
Classifier: License :: OSI Approved :: GNU General Public License v3 or later (GPLv3+)
Classifier: Programming Language :: Python :: 3
Classifier: Programming Language :: Python :: 3.12
Classifier: Programming Language :: Python :: 3.13
Requires-Dist: mnllib (>=0.2.0,<0.3.0)
Requires-Dist: ndspy (>=4.2.0,<5.0.0)
Requires-Dist: tqdm (>=4.67.1,<5.0.0)
Project-URL: Repository, https://github.com/MnL-Modding/mnltools.py
